demox2004/__init__.py
demox2004/demox2004.py
demox2004-0.1.dist-info/LICENSE
demox2004-0.1.dist-info/METADATA
demox2004-0.1.dist-info/WHEEL
demox2004-0.1.dist-info/top_level.txt
demox2004-0.1.dist-info/RECORD
